README.md
setup.py
app/__init__.py
app/alarm/__init__.py
app/alarm/endpoints.py
app/alarm/transports.py
app/app_service/__init__.py
app/app_service/app/__init__.py
app/app_service/app/endpoints.py
app/app_service/app/transports.py
app/app_service/app_service/__init__.py
app/app_service/app_service/endpoints.py
app/app_service/app_service/transports.py
app/authdns_zone/__init__.py
app/authdns_zone/endpoints.py
app/authdns_zone/transports.py
app/cdn/__init__.py
app/cdn/ingress_host/__init__.py
app/cdn/ingress_host/endpoints.py
app/cdn/ingress_host/transports.py
app/cdn/origin/__init__.py
app/cdn/origin/endpoints.py
app/cdn/origin/transports.py
app/cdn/policy/__init__.py
app/cdn/policy/endpoints.py
app/cdn/policy/transports.py
app/cdn/service/__init__.py
app/cdn/service/endpoints.py
app/cdn/service/transports.py
app/cdn/service_group/__init__.py
app/cdn/service_group/endpoints.py
app/cdn/service_group/transports.py
app/common/__init__.py
app/common/consts.py
app/common/endpoints.py
app/common/errors.py
app/common/transports.py
app/dns_app_service/__init__.py
app/dns_app_service/endpoints.py
app/dns_app_service/transports.py
app/gts/__init__.py
app/gts/policy/__init__.py
app/gts/policy/endpoints.py
app/gts/policy/transports.py
app/gts/region/__init__.py
app/gts/region/endpoints.py
app/gts/region/transports.py
app/gts/region_map/__init__.py
app/gts/region_map/endpoints.py
app/gts/region_map/transports.py
app/gts/ruleset/__init__.py
app/gts/ruleset/endpoints.py
app/gts/ruleset/transports.py
app/gts/view/__init__.py
app/gts/view/endpoints.py
app/gts/view/transports.py
app/gts/zones/__init__.py
app/gts/zones/endpoints.py
app/gts/zones/transports.py
app/health_monitors/__init__.py
app/health_monitors/endpoints.py
app/health_monitors/transports.py
app/service_group/__init__.py
app/service_group/endpoints.py
app/service_group/transports.py
dingman/__init__.py
dingman/cli_pb2.py
dingman/cli_pb2_grpc.py
openapi_server/__init__.py
openapi_server/__main__.py
openapi_server.egg-info/PKG-INFO
openapi_server.egg-info/SOURCES.txt
openapi_server.egg-info/dependency_links.txt
openapi_server.egg-info/requires.txt
openapi_server.egg-info/top_level.txt
