Metadata-Version: 2.1
Name: openapi-server
Version: 1.0.17
Summary: CDN DMS Open API
Home-page: https://code.byted.org/savanna/dingman_api_server
Author: BD Data Sys IE CDN
Requires-Python: >=3.7
